LICENSE
MANIFEST.in
README.md
nodemaster.py
setup.py
nodemaster.egg-info/PKG-INFO
nodemaster.egg-info/SOURCES.txt
nodemaster.egg-info/dependency_links.txt
nodemaster.egg-info/entry_points.txt
nodemaster.egg-info/top_level.txt