Metadata-Version: 1.0
Name: nodemaster
Version: 2017.1.16.1608
Summary: node control utilities
Home-page: https://github.com/wdbm/nodemaster
Author: Will Breaden Madden
Author-email: wbm@protonmail.ch
License: GPLv3
Platform: UNKNOWN
